state1/__init__.py
state1/actions.py
state1/agent.py
state1/orchestrator.py
state1/terminal_chat.py
state1-0.6.7.dist-info/licenses/LICENSE
tests/demo_chat.py
tests/test_agent.py
state1-0.6.7.dist-info/METADATA
state1-0.6.7.dist-info/WHEEL
state1-0.6.7.dist-info/entry_points.txt
state1-0.6.7.dist-info/top_level.txt
state1-0.6.7.dist-info/RECORD
