Metadata-Version: 2.4
Name: State1
Version: 0.6.7
Summary: A unified framework for building AI agents with low-code.
Author-email: Udit Akhouri <researchudit@gmail.com>, Exthalpy Technologies <udit@exthalpy.com>
Project-URL: Homepage, https://github.com/Exthalpy/state1
Requires-Python: >=3.8
License-File: LICENSE
Requires-Dist: openai
Requires-Dist: requests
Requires-Dist: duckduckgo-search
Requires-Dist: sentence-transformers
Requires-Dist: chromadb
Requires-Dist: PyPDF2
Requires-Dist: python-docx
Requires-Dist: termcolor
Requires-Dist: bcrypt
Dynamic: license-file
